.gitignore
CHANGES.txt
CONTRIBUTORS.txt
MANIFEST.in
README.rst
setup.py
docs/LICENSE.GPL
docs/LICENSE.txt
src/raptus/__init__.py
src/raptus.touchswipe.egg-info/PKG-INFO
src/raptus.touchswipe.egg-info/SOURCES.txt
src/raptus.touchswipe.egg-info/dependency_links.txt
src/raptus.touchswipe.egg-info/entry_points.txt
src/raptus.touchswipe.egg-info/namespace_packages.txt
src/raptus.touchswipe.egg-info/not-zip-safe
src/raptus.touchswipe.egg-info/requires.txt
src/raptus.touchswipe.egg-info/top_level.txt
src/raptus/touchswipe/__init__.py
src/raptus/touchswipe/configure.zcml
src/raptus/touchswipe/jquery.touchSwipe.min.js
src/raptus/touchswipe/profiles/default/jsregistry.xml
src/raptus/touchswipe/profiles/default/metadata.xml