Metadata-Version: 1.1
Name: raptus.touchswipe
Version: 1.0a1
Summary: Provides the jQuery TouchSwipe plugin as Plone JS resource
Home-page: http://github.com/Raptus/raptus.touchswipe
Author: Raptus AG
Author-email: dev@raptus.com
License: gpl
Platform: UNKNOWN
Classifier: Programming Language :: Python
